Metadata-Version: 2.1
Name: bob.buildout
Version: 2.4.0
Summary: A collection of zc.buildout recipes for Bob packages
Home-page: https://gitlab.idiap.ch/bob/bob.buildout
Author: Andre Anjos
Author-email: andre.anjos@idiap.ch
License: BSD
Keywords: buildout,sphinx,nose,recipe,eggs,bob
Platform: UNKNOWN
Classifier: Framework :: Bob
Classifier: Development Status :: 5 - Production/Stable
Classifier: Environment :: Plugins
Classifier: Framework :: Buildout :: Recipe
Classifier: Intended Audience :: Developers
Classifier: License :: OSI Approved :: BSD License
Classifier: Topic :: Software Development :: Build Tools
Classifier: Topic :: Software Development :: Libraries :: Python Modules
Classifier: Natural Language :: English
Classifier: Programming Language :: Python
Classifier: Programming Language :: Python :: 3
License-File: LICENSE
